{
  "summary": "Completed comprehensive end-to-end testing of Library Book Tracking System. All backend APIs and frontend functionality tested successfully.",
  "backend_issues": {
    "critical_bugs": [],
    "flaky_endpoints": []
  },
  "frontend_issues": {
    "ui_bugs": [],
    "integration_issues": [],
    "design_issues": []
  },
  "passed_tests": [
    "Login functionality (valid and invalid username)",
    "Dashboard statistics display and API integration",
    "Books CRUD operations (Create, Read, Update, Delete)",
    "Search functionality by title and author",
    "Navigation between Dashboard and Books pages",
    "Book management modal operations (add/edit/close)",
    "Table view display with proper formatting",
    "Status updates (available/issued)",
    "Logout functionality with proper redirection",
    "Error handling for duplicate books and non-existent records",
    "Frontend-backend API integration",
    "User authentication persistence",
    "Responsive UI design and styling"
  ],
  "test_report_links": ["/app/backend_test.py"],
  "success_percentage": {
    "backend": "100% (14/14 tests passed)",
    "frontend": "100% (all major functionality working)",
    "integration": "100% (frontend-backend communication working)"
  },
  "updated_files": ["/app/backend_test.py"],
  "action_item_for_main_agent": "",
  "should_call_test_agent_after_fix": "false",
  "should_main_agent_test_itself": "false"
}